setup.py
vivisect_vstruct_wb.egg-info/PKG-INFO
vivisect_vstruct_wb.egg-info/SOURCES.txt
vivisect_vstruct_wb.egg-info/dependency_links.txt
vivisect_vstruct_wb.egg-info/top_level.txt
vstruct/__init__.py
vstruct/bitfield.py
vstruct/builder.py
vstruct/cparse.py
vstruct/primitives.py